flake8_cohesion/__init__.py
flake8_cohesion/extension.py
flake8_cohesion/module.py
flake8_cohesion/parser.py
flake8_cohesion-1.0.1.dist-info/entry_points.txt
flake8_cohesion-1.0.1.dist-info/WHEEL
flake8_cohesion-1.0.1.dist-info/METADATA
flake8_cohesion-1.0.1.dist-info/licenses/LICENSE
flake8_cohesion-1.0.1.dist-info/RECORD
